Metadata-Version: 2.1
Name: eitaayar
Version: 1.0.1
Summary: This is an almost official library for managing and building bots in eitaa Messenger...
Home-page: https://github.com/snipe4kill/eitaayar/
Author: Shayan Heidari
Author-email: snipe4kill.tg@gmail.com
License: UNKNOWN
Platform: UNKNOWN
Classifier: Programming Language :: Python :: 3.6
Classifier: Programming Language :: Python :: 3.7
Classifier: Programming Language :: Python :: 3.8
Classifier: Programming Language :: Python :: 3.9
Classifier: Programming Language :: Python :: 3.10
Classifier: Programming Language :: Python :: 3.11
Classifier: License :: OSI Approved :: MIT License
